{
  "web": {
    "client_id": "download your client_secrets.json from youtube api console",
    "project_id": "download your client_secrets.json from youtube api console",
    "auth_uri": "download your client_secrets.json from youtube api console",
    "token_uri": "download your client_secrets.json from youtube api console",
    "auth_provider_x509_cert_url": "download your client_secrets.json from youtube api console",
    "client_secret": "download your client_secrets.json from youtube api console",
    "redirect_uris": [
      "http://localhost:8080",
      "https://localhost:8080",
      "http://localhost:8080/"
    ]
  }
}